bcrxpt/__init__.py
bcrxpt-4.1.2.dist-info/METADATA
bcrxpt-4.1.2.dist-info/WHEEL
bcrxpt-4.1.2.dist-info/RECORD
