Metadata-Version: 2.1
Name: bcrxpt
Version: 4.1.2
Summary: Bitsquatting security research
License: Public Domain in the US or CC0 outside
Author: Carl Schroedl
Author-email: cschroedl@usgs.gov
Requires-Python: >=3.11,<4.0
Classifier: License :: Other/Proprietary License
Classifier: Programming Language :: Python :: 3
Classifier: Programming Language :: Python :: 3.11
Classifier: Programming Language :: Python :: 3.12
